MANIFEST.in
README.md
setup.py
examples/__init__.py
examples/testcase.py
pyunitreport/__init__.py
pyunitreport/result.py
pyunitreport/runner.py
pyunitreport.egg-info/PKG-INFO
pyunitreport.egg-info/SOURCES.txt
pyunitreport.egg-info/dependency_links.txt
pyunitreport.egg-info/not-zip-safe
pyunitreport.egg-info/requires.txt
pyunitreport.egg-info/top_level.txt
pyunitreport/template/report_template.html