Metadata-Version: 1.1
Name: pyunitreport
Version: 0.1.4
Summary: A unit test runner for Python, and generate HTML reports.
Home-page: https://github.com/HttpRunner/PyUnitReport
Author: Ordanis Sanchez Suero, Leo Lee
Author-email: mail@debugtalk.com
License: MIT license
Keywords: HtmlTestRunner TestRunner Html Reports
Platform: UNKNOWN
Classifier: Development Status :: 3 - Alpha
Classifier: Intended Audience :: Developers
Classifier: License :: OSI Approved :: MIT License
Classifier: Natural Language :: English
Classifier: Programming Language :: Python :: 2.7
Classifier: Programming Language :: Python :: 3.3
Classifier: Programming Language :: Python :: 3.4
Classifier: Programming Language :: Python :: 3.5
Classifier: Programming Language :: Python :: 3.6
